anujscan/__init__.py
anujscan/__main__.py
anujscan/gui.py
anujscan/toolkit.py
anujscan/assets/logo.png
anujscan/data/__init__.py
anujscan/data/common.txt
anujscan/modules/__init__.py
anujscan/modules/banner_grabber.py
anujscan/modules/brute_forcer.py
anujscan/modules/dir_bruteforce.py
anujscan/modules/port_scanner.py
anujscan/modules/subdomain_scanner.py
anujscan/modules/whois_lookup.py
anujscan-1.0.0.dist-info/METADATA
anujscan-1.0.0.dist-info/WHEEL
anujscan-1.0.0.dist-info/entry_points.txt
anujscan-1.0.0.dist-info/top_level.txt
anujscan-1.0.0.dist-info/RECORD
