Metadata-Version: 2.4
Name: anujscan
Version: 1.0.0
Summary: AnujScan - GUI-based Penetration Testing Toolkit
Author: Anuj Prajapati
Author-email: anujprajapati2109@gmail.com
Classifier: Programming Language :: Python :: 3
Classifier: Operating System :: OS Independent
Requires-Python: >=3.7
Requires-Dist: pillow
Requires-Dist: requests
Requires-Dist: whois
Dynamic: author
Dynamic: author-email
Dynamic: classifier
Dynamic: requires-dist
Dynamic: requires-python
Dynamic: summary
